{"result": {"query": ":facetid:toc:\"db/conf/middleware/middleware2021.bht\"", "status": {"@code": "200", "text": "OK"}, "time": {"@unit": "msecs", "text": "183.40"}, "completions": {"@total": "1", "@computed": "1", "@sent": "1", "c": {"@sc": "30", "@dc": "30", "@oc": "30", "@id": "40456931", "text": ":facetid:toc:db/conf/middleware/middleware2021.bht"}}, "hits": {"@total": "30", "@computed": "30", "@sent": "30", "@first": "0", "hit": [{"@score": "1", "@id": "999617", "info": {"authors": {"author": [{"@pid": "69/1023", "text": "Marc S\u00e1nchez Artigas"}, {"@pid": "310/1827", "text": "Pablo Gimeno Sarroca"}]}, "title": "Experience Paper: Towards enhancing cost efficiency in serverless machine learning training.", "venue": "Middleware", "pages": "210-222", "year": "2021", "type": "Conference and Workshop Papers", "access": "closed", "key": "conf/middleware/ArtigasS21", "doi": "10.1145/3464298.3494884", "ee": "https://doi.org/10.1145/3464298.3494884", "url": "https://dblp.org/rec/conf/middleware/ArtigasS21"}, "url": "URL#999617"}, {"@score": "1", "@id": "999618", "info": {"authors": {"author": [{"@pid": "179/7953", "text": "Jossekin Beilharz"}, {"@pid": "243/2965", "text": "Bjarne Pfitzner"}, {"@pid": "66/2459", "text": "Robert Schmid"}, {"@pid": "305/3792", "text": "Paul Geppert"}, {"@pid": "63/152", "text": "Bert Arnrich"}, {"@pid": "p/AndreasPolze", "text": "Andreas Polze"}]}, "title": "Implicit model specialization through dag-based decentralized federated learning.", "venue": "Middleware", "pages": "310-322", "year": "2021", "type": "Conference and Workshop Papers", "access": "closed", "key": "conf/middleware/BeilharzPSGAP21", "doi": "10.1145/3464298.3493403", "ee": "https://doi.org/10.1145/3464298.3493403", "url": "https://dblp.org/rec/conf/middleware/BeilharzPSGAP21"}, "url": "URL#999618"}, {"@score": "1", "@id": "999624", "info": {"authors": {"author": [{"@pid": "160/1777", "text": "Daniel Cason"}, {"@pid": "64/181", "text": "Nenad Milosevic"}, {"@pid": "74/7594-1", "text": "Zarko Milosevic 0001"}, {"@pid": "90/2612", "text": "Fernando Pedone"}]}, "title": "Gossip consensus.", "venue": "Middleware", "pages": "198-209", "year": "2021", "type": "Conference and Workshop Papers", "access": "closed", "key": "conf/middleware/CasonM0P21", "doi": "10.1145/3464298.3493395", "ee": "https://doi.org/10.1145/3464298.3493395", "url": "https://dblp.org/rec/conf/middleware/CasonM0P21"}, "url": "URL#999624"}, {"@score": "1", "@id": "999625", "info": {"authors": {"author": [{"@pid": "187/2708", "text": "Marcin Copik"}, {"@pid": "147/3417", "text": "Grzegorz Kwasniewski"}, {"@pid": "136/7953", "text": "Maciej Besta"}, {"@pid": "201/7835", "text": "Michal Podstawski"}, {"@pid": "16/3869", "text": "Torsten Hoefler"}]}, "title": "SeBS: a serverless benchmark suite for function-as-a-service computing.", "venue": "Middleware", "pages": "64-78", "year": "2021", "type": "Conference and Workshop Papers", "access": "closed", "key": "conf/middleware/CopikKBPH21", "doi": "10.1145/3464298.3476133", "ee": "https://doi.org/10.1145/3464298.3476133", "url": "https://dblp.org/rec/conf/middleware/CopikKBPH21"}, "url": "URL#999625"}, {"@score": "1", "@id": "999626", "info": {"authors": {"author": [{"@pid": "49/8419", "text": "Giuseppe Coviello"}, {"@pid": "33/4854-18", "text": "Yi Yang 0018"}, {"@pid": "44/10367", "text": "Kunal Rao"}, {"@pid": "28/3799", "text": "Srimat T. Chakradhar"}]}, "title": "Magic-Pipe: self-optimizing video analytics pipelines.", "venue": "Middleware", "pages": "79-90", "year": "2021", "type": "Conference and Workshop Papers", "access": "closed", "key": "conf/middleware/Coviello0RC21", "doi": "10.1145/3464298.3484504", "ee": "https://doi.org/10.1145/3464298.3484504", "url": "https://dblp.org/rec/conf/middleware/Coviello0RC21"}, "url": "URL#999626"}, {"@score": "1", "@id": "999629", "info": {"authors": {"author": [{"@pid": "82/8491", "text": "Xiaoming Du"}, {"@pid": "74/3487", "text": "Cong Li"}]}, "title": "SHARC: improving adaptive replacement cache with shadow recency cache management.", "venue": "Middleware", "pages": "119-131", "year": "2021", "type": "Conference and Workshop Papers", "access": "closed", "key": "conf/middleware/DuL21", "doi": "10.1145/3464298.3493389", "ee": "https://doi.org/10.1145/3464298.3493389", "url": "https://dblp.org/rec/conf/middleware/DuL21"}, "url": "URL#999629"}, {"@score": "1", "@id": "999631", "info": {"authors": {"author": [{"@pid": "178/4172", "text": "Simon Eismann"}, {"@pid": "160/0251", "text": "Long Bui"}, {"@pid": "204/3835", "text": "Johannes Grohmann"}, {"@pid": "88/282", "text": "Cristina L. Abad"}, {"@pid": "130/4084", "text": "Nikolas Herbst"}, {"@pid": "k/SamuelKounev", "text": "Samuel Kounev"}]}, "title": "Sizeless: predicting the optimal size of serverless functions.", "venue": "Middleware", "pages": "248-259", "year": "2021", "type": "Conference and Workshop Papers", "access": "closed", "key": "conf/middleware/EismannBGAHK21", "doi": "10.1145/3464298.3493398", "ee": "https://doi.org/10.1145/3464298.3493398", "url": "https://dblp.org/rec/conf/middleware/EismannBGAHK21"}, "url": "URL#999631"}, {"@score": "1", "@id": "999635", "info": {"authors": {"author": [{"@pid": "257/9777", "text": "T\u00e2nia Esteves"}, {"@pid": "200/5706", "text": "Francisco Neves"}, {"@pid": "41/3634-1", "text": "Rui Oliveira 0001"}, {"@pid": "128/5697-1", "text": "Jo\u00e3o Paulo 0001"}]}, "title": "CAT: content-aware tracing and analysis for distributed systems.", "venue": "Middleware", "pages": "223-235", "year": "2021", "type": "Conference and Workshop Papers", "access": "closed", "key": "conf/middleware/EstevesNO021", "doi": "10.1145/3464298.3493396", "ee": "https://doi.org/10.1145/3464298.3493396", "url": "https://dblp.org/rec/conf/middleware/EstevesNO021"}, "url": "URL#999635"}, {"@score": "1", "@id": "999639", "info": {"authors": {"author": [{"@pid": "176/5684", "text": "Ubaid Ullah Hafeez"}, {"@pid": "30/202-4", "text": "Xiao Sun 0004"}, {"@pid": "62/2403", "text": "Anshul Gandhi"}, {"@pid": "02/1825-2", "text": "Zhenhua Liu 0002"}]}, "title": "Towards optimal placement and scheduling of DNN operations with Pesto.", "venue": "Middleware", "pages": "39-51", "year": "2021", "type": "Conference and Workshop Papers", "access": "closed", "key": "conf/middleware/HafeezSG021", "doi": "10.1145/3464298.3476132", "ee": "https://doi.org/10.1145/3464298.3476132", "url": "https://dblp.org/rec/conf/middleware/HafeezSG021"}, "url": "URL#999639"}, {"@score": "1", "@id": "999640", "info": {"authors": {"author": [{"@pid": "305/0439", "text": "Edson Horta"}, {"@pid": "198/2549", "text": "Ho-Ren Chuang"}, {"@pid": "305/0074", "text": "Naarayanan Rao VSathish"}, {"@pid": "305/0521", "text": "Cesar Philippidis"}, {"@pid": "132/0327", "text": "Antonio Barbalace"}, {"@pid": "97/9808", "text": "Pierre Olivier"}, {"@pid": "61/2985", "text": "Binoy Ravindran"}]}, "title": "Xar-trek: run-time execution migration among FPGAs and heterogeneous-ISA CPUs.", "venue": "Middleware", "pages": "104-118", "year": "2021", "type": "Conference and Workshop Papers", "access": "closed", "key": "conf/middleware/HortaCVPBOR21", "doi": "10.1145/3464298.3493388", "ee": "https://doi.org/10.1145/3464298.3493388", "url": "https://dblp.org/rec/conf/middleware/HortaCVPBOR21"}, "url": "URL#999640"}, {"@score": "1", "@id": "999643", "info": {"authors": {"author": [{"@pid": "152/3938", "text": "Giorgos Kappes"}, {"@pid": "67/568", "text": "Stergios V. Anastasiadis"}]}, "title": "Experience Paper: Danaus: isolation and efficiency of container I/O at the client side of network storage.", "venue": "Middleware", "pages": "132-145", "year": "2021", "type": "Conference and Workshop Papers", "access": "closed", "key": "conf/middleware/KappesA21", "doi": "10.1145/3464298.3493390", "ee": "https://doi.org/10.1145/3464298.3493390", "url": "https://dblp.org/rec/conf/middleware/KappesA21"}, "url": "URL#999643"}, {"@score": "1", "@id": "999645", "info": {"authors": {"author": [{"@pid": "283/5555", "text": "Rabimba Karanjai"}, {"@pid": "19/360-12", "text": "Lei Xu 0012"}, {"@pid": "146/2661", "text": "Zhimin Gao"}, {"@pid": "13/3479-9", "text": "Lin Chen 0009"}, {"@pid": "261/3403", "text": "Mudabbir Kaleem"}, {"@pid": "73/5220", "text": "Weidong Shi"}]}, "title": "Privacy preserving event based transaction system in a decentralized environment.", "venue": "Middleware", "pages": "286-297", "year": "2021", "type": "Conference and Workshop Papers", "access": "closed", "key": "conf/middleware/KaranjaiXGCKS21", "doi": "10.1145/3464298.3493401", "ee": "https://doi.org/10.1145/3464298.3493401", "url": "https://dblp.org/rec/conf/middleware/KaranjaiXGCKS21"}, "url": "URL#999645"}, {"@score": "1", "@id": "999647", "info": {"authors": {"author": [{"@pid": "210/6085", "text": "Masoomeh Javidi Kishi"}, {"@pid": "09/7950", "text": "Roberto Palmieri"}]}, "title": "FW-KV: improving read guarantees in PSI.", "venue": "Middleware", "pages": "27-38", "year": "2021", "type": "Conference and Workshop Papers", "access": "closed", "key": "conf/middleware/KishiP21", "doi": "10.1145/3464298.3476131", "ee": "https://doi.org/10.1145/3464298.3476131", "url": "https://dblp.org/rec/conf/middleware/KishiP21"}, "url": "URL#999647"}, {"@score": "1", "@id": "999650", "info": {"authors": {"author": [{"@pid": "270/6348", "text": "Long Hoang Le"}, {"@pid": "252/1324", "text": "Mojtaba Eslahi-Kelorazi"}, {"@pid": "205/3768", "text": "Paulo R. Coelho"}, {"@pid": "90/2612", "text": "Fernando Pedone"}]}, "title": "RamCast: RDMA-based atomic multicast.", "venue": "Middleware", "pages": "172-184", "year": "2021", "type": "Conference and Workshop Papers", "access": "closed", "key": "conf/middleware/LeECP21", "doi": "10.1145/3464298.3493393", "ee": "https://doi.org/10.1145/3464298.3493393", "url": "https://dblp.org/rec/conf/middleware/LeECP21"}, "url": "URL#999650"}, {"@score": "1", "@id": "999655", "info": {"authors": {"author": [{"@pid": "310/1705", "text": "Taras Lykhenko"}, {"@pid": "49/2065", "text": "Rafael Soares"}, {"@pid": "r/LRodrigues", "text": "Lu\u00eds Rodrigues 0001"}]}, "title": "FaaSTCC: efficient transactional causal consistency for serverless computing.", "venue": "Middleware", "pages": "159-171", "year": "2021", "type": "Conference and Workshop Papers", "access": "closed", "key": "conf/middleware/LykhenkoSR21", "doi": "10.1145/3464298.3493392", "ee": "https://doi.org/10.1145/3464298.3493392", "url": "https://dblp.org/rec/conf/middleware/LykhenkoSR21"}, "url": "URL#999655"}, {"@score": "1", "@id": "999658", "info": {"authors": {"author": [{"@pid": "223/7104", "text": "Ines Messadi"}, {"@pid": "253/7203", "text": "Shivananda Neumann"}, {"@pid": "185/6233", "text": "Nico Weichbrodt"}, {"@pid": "253/7142", "text": "Lennart Almstedt"}, {"@pid": "297/5552", "text": "Mohammad Mahhouk"}, {"@pid": "27/2697", "text": "R\u00fcdiger Kapitza"}]}, "title": "Precursor: a fast, client-centric and trusted key-value store using RDMA and Intel SGX.", "venue": "Middleware", "pages": "1-13", "year": "2021", "type": "Conference and Workshop Papers", "access": "closed", "key": "conf/middleware/MessadiNWAMK21", "doi": "10.1145/3464298.3476129", "ee": "https://doi.org/10.1145/3464298.3476129", "url": "https://dblp.org/rec/conf/middleware/MessadiNWAMK21"}, "url": "URL#999658"}, {"@score": "1", "@id": "999662", "info": {"authors": {"author": [{"@pid": "239/8528", "text": "Racin Nygaard"}, {"@pid": "17/7673", "text": "Vero Estrada-Gali\u00f1anes"}, {"@pid": "59/2296", "text": "Hein Meling"}]}, "title": "Snarl: entangled merkle trees for improved file availability and storage utilization.", "venue": "Middleware", "pages": "236-247", "year": "2021", "type": "Conference and Workshop Papers", "access": "closed", "key": "conf/middleware/NygaardEM21", "doi": "10.1145/3464298.3493397", "ee": "https://doi.org/10.1145/3464298.3493397", "url": "https://dblp.org/rec/conf/middleware/NygaardEM21"}, "url": "URL#999662"}, {"@score": "1", "@id": "999664", "info": {"authors": {"author": [{"@pid": "183/0883", "text": "Dimitris Palyvos-Giannas"}, {"@pid": "85/5541", "text": "Gabriele Mencagli"}, {"@pid": "p/MPapatriantafilou", "text": "Marina Papatriantafilou"}, {"@pid": "13/8330", "text": "Vincenzo Gulisano"}]}, "title": "Lachesis: a middleware for customizing OS scheduling of stream processing queries.", "venue": "Middleware", "pages": "365-378", "year": "2021", "type": "Conference and Workshop Papers", "access": "closed", "key": "conf/middleware/Palyvos-Giannas21", "doi": "10.1145/3464298.3493407", "ee": "https://doi.org/10.1145/3464298.3493407", "url": "https://dblp.org/rec/conf/middleware/Palyvos-Giannas21"}, "url": "URL#999664"}, {"@score": "1", "@id": "999665", "info": {"authors": {"author": [{"@pid": "206/4519", "text": "Aidi Pi"}, {"@pid": "259/7298", "text": "Junxian Zhao"}, {"@pid": "156/4566", "text": "Shaoqi Wang"}, {"@pid": "13/6395-2", "text": "Xiaobo Zhou 0002"}]}, "title": "Memory at your service: fast memory allocation for latency-critical services.", "venue": "Middleware", "pages": "185-197", "year": "2021", "type": "Conference and Workshop Papers", "access": "closed", "key": "conf/middleware/PiZW021", "doi": "10.1145/3464298.3493394", "ee": "https://doi.org/10.1145/3464298.3493394", "url": "https://dblp.org/rec/conf/middleware/PiZW021"}, "url": "URL#999665"}, {"@score": "1", "@id": "999672", "info": {"authors": {"author": [{"@pid": "304/7731", "text": "Vincent van Rijn"}, {"@pid": "21/4498", "text": "Jan S. Rellermeyer"}]}, "title": "A fresh look at the architecture and performance of contemporary isolation platforms.", "venue": "Middleware", "pages": "323-335", "year": "2021", "type": "Conference and Workshop Papers", "access": "closed", "key": "conf/middleware/RijnR21", "doi": "10.1145/3464298.3493404", "ee": "https://doi.org/10.1145/3464298.3493404", "url": "https://dblp.org/rec/conf/middleware/RijnR21"}, "url": "URL#999672"}, {"@score": "1", "@id": "999674", "info": {"authors": {"author": [{"@pid": "193/7730", "text": "Guillaume Rosinosky"}, {"@pid": "222/1281", "text": "Simon Da Silva"}, {"@pid": "b/SoniaBenMokhtar", "text": "Sonia Ben Mokhtar"}, {"@pid": "51/6683", "text": "Daniel N\u00e9gru"}, {"@pid": "11/1262", "text": "Laurent R\u00e9veill\u00e8re"}, {"@pid": "01/6018", "text": "Etienne Rivi\u00e8re"}]}, "title": "PProx: efficient privacy for recommendation-as-a-service.", "venue": "Middleware", "pages": "14-26", "year": "2021", "type": "Conference and Workshop Papers", "access": "closed", "key": "conf/middleware/RosinoskySMNRR21", "doi": "10.1145/3464298.3476130", "ee": "https://doi.org/10.1145/3464298.3476130", "url": "https://dblp.org/rec/conf/middleware/RosinoskySMNRR21"}, "url": "URL#999674"}, {"@score": "1", "@id": "999675", "info": {"authors": {"author": [{"@pid": "168/9566", "text": "Benjamin Rouxel"}, {"@pid": "62/3654", "text": "Sebastian Altmeyer"}, {"@pid": "54/1303", "text": "Clemens Grelck"}]}, "title": "YASMIN: a real-time middleware for COTS heterogeneous platforms.", "venue": "Middleware", "pages": "298-309", "year": "2021", "type": "Conference and Workshop Papers", "access": "closed", "key": "conf/middleware/RouxelAG21", "doi": "10.1145/3464298.3493402", "ee": "https://doi.org/10.1145/3464298.3493402", "url": "https://dblp.org/rec/conf/middleware/RouxelAG21"}, "url": "URL#999675"}, {"@score": "1", "@id": "999680", "info": {"authors": {"author": [{"@pid": "10/6711", "text": "Byungchul Tak"}, {"@pid": "62/2450", "text": "Wook-Shin Han"}]}, "title": "Lognroll: discovering accurate log templates by iterative filtering.", "venue": "Middleware", "pages": "273-285", "year": "2021", "type": "Conference and Workshop Papers", "access": "closed", "key": "conf/middleware/TakH21", "doi": "10.1145/3464298.3493400", "ee": "https://doi.org/10.1145/3464298.3493400", "url": "https://dblp.org/rec/conf/middleware/TakH21"}, "url": "URL#999680"}, {"@score": "1", "@id": "999681", "info": {"authors": {"author": [{"@pid": "310/1901", "text": "Ilyas Toumlilt"}, {"@pid": "09/5760", "text": "Pierre Sutra"}, {"@pid": "s/MarcShapiro", "text": "Marc Shapiro 0001"}]}, "title": "Highly-available and consistent group collaboration at the edge with colony.", "venue": "Middleware", "pages": "336-351", "year": "2021", "type": "Conference and Workshop Papers", "access": "closed", "key": "conf/middleware/ToumliltS021", "doi": "10.1145/3464298.3493405", "ee": "https://doi.org/10.1145/3464298.3493405", "url": "https://dblp.org/rec/conf/middleware/ToumliltS021"}, "url": "URL#999681"}, {"@score": "1", "@id": "999682", "info": {"authors": {"author": [{"@pid": "185/6233", "text": "Nico Weichbrodt"}, {"@pid": "305/9110", "text": "Joshua Heinemann"}, {"@pid": "253/7142", "text": "Lennart Almstedt"}, {"@pid": "139/0414", "text": "Pierre-Louis Aublin"}, {"@pid": "27/2697", "text": "R\u00fcdiger Kapitza"}]}, "title": "sgx-dl: dynamic loading and hot-patching for secure applications: experience paper.", "venue": "Middleware", "pages": "91-103", "year": "2021", "type": "Conference and Workshop Papers", "access": "closed", "key": "conf/middleware/WeichbrodtHAAK21", "doi": "10.1145/3464298.3476134", "ee": "https://doi.org/10.1145/3464298.3476134", "url": "https://dblp.org/rec/conf/middleware/WeichbrodtHAAK21"}, "url": "URL#999682"}, {"@score": "1", "@id": "999683", "info": {"authors": {"author": [{"@pid": "237/1045", "text": "Philipp Wiesner"}, {"@pid": "224/1515", "text": "Ilja Behnke"}, {"@pid": "286/5159", "text": "Dominik Scheinert"}, {"@pid": "285/5017", "text": "Kain Kordian Gontarska"}, {"@pid": "59/11337", "text": "Lauritz Thamsen"}]}, "title": "Let&apos;s wait awhile: how temporal workload shifting can reduce carbon emissions in the cloud.", "venue": "Middleware", "pages": "260-272", "year": "2021", "type": "Conference and Workshop Papers", "access": "closed", "key": "conf/middleware/WiesnerBSGT21", "doi": "10.1145/3464298.3493399", "ee": "https://doi.org/10.1145/3464298.3493399", "url": "https://dblp.org/rec/conf/middleware/WiesnerBSGT21"}, "url": "URL#999683"}, {"@score": "1", "@id": "999684", "info": {"authors": {"author": [{"@pid": "62/3426", "text": "Xiaofeng Wu"}, {"@pid": "38/618", "text": "Jia Rao"}, {"@pid": "c/WeiChen38", "text": "Wei Chen 0038"}, {"@pid": "05/125", "text": "Hang Huang"}, {"@pid": "d/CHQDing", "text": "Chris H. Q. Ding"}, {"@pid": "03/281", "text": "Heng Huang"}]}, "title": "SwitchFlow: preemptive multitasking for deep learning.", "venue": "Middleware", "pages": "146-158", "year": "2021", "type": "Conference and Workshop Papers", "access": "closed", "key": "conf/middleware/WuR0HDH21", "doi": "10.1145/3464298.3493391", "ee": "https://doi.org/10.1145/3464298.3493391", "url": "https://dblp.org/rec/conf/middleware/WuR0HDH21"}, "url": "URL#999684"}, {"@score": "1", "@id": "999686", "info": {"authors": {"author": [{"@pid": "266/7540", "text": "Peterson Yuhala"}, {"@pid": "289/2287", "text": "J\u00e4mes M\u00e9n\u00e9trey"}, {"@pid": "f/PascalFelber", "text": "Pascal Felber"}, {"@pid": "15/2850", "text": "Valerio Schiavoni"}, {"@pid": "77/2224", "text": "Alain Tchana"}, {"@pid": "83/6740-1", "text": "Ga\u00ebl Thomas 0001"}, {"@pid": "182/6438", "text": "Hugo Guiroux"}, {"@pid": "133/3713", "text": "Jean-Pierre Lozi"}]}, "title": "Montsalvat: Intel SGX shielding for GraalVM native images.", "venue": "Middleware", "pages": "352-364", "year": "2021", "type": "Conference and Workshop Papers", "access": "closed", "key": "conf/middleware/YuhalaMFST0GL21", "doi": "10.1145/3464298.3493406", "ee": "https://doi.org/10.1145/3464298.3493406", "url": "https://dblp.org/rec/conf/middleware/YuhalaMFST0GL21"}, "url": "URL#999686"}, {"@score": "1", "@id": "999687", "info": {"authors": {"author": [{"@pid": "228/4392", "text": "Gengrui Zhang"}, {"@pid": "j/HansArnoJacobsen", "text": "Hans-Arno Jacobsen"}]}, "title": "Prosecutor: an efficient BFT consensus algorithm with behavior-aware penalization against Byzantine attacks.", "venue": "Middleware", "pages": "52-63", "year": "2021", "type": "Conference and Workshop Papers", "access": "closed", "key": "conf/middleware/ZhangJ21", "doi": "10.1145/3464298.3484503", "ee": "https://doi.org/10.1145/3464298.3484503", "url": "https://dblp.org/rec/conf/middleware/ZhangJ21"}, "url": "URL#999687"}, {"@score": "1", "@id": "1043246", "info": {"authors": {"author": [{"@pid": "12/4550-1", "text": "Kaiwen Zhang 0001"}, {"@pid": "55/1758", "text": "Abdelouahed Gherbi"}, {"@pid": "66/1875", "text": "Nalini Venkatasubramanian"}, {"@pid": "v/LuisVeiga", "text": "Lu\u00eds Veiga"}]}, "title": "Middleware &apos;21: 22nd International Middleware Conference, Qu\u00e9bec City, Canada, December 6 - 10, 2021", "venue": "Middleware", "publisher": "ACM", "year": "2021", "type": "Editorship", "key": "conf/middleware/2021", "doi": "10.1145/3464298", "ee": "https://doi.org/10.1145/3464298", "url": "https://dblp.org/rec/conf/middleware/2021"}, "url": "URL#1043246"}]}}}