{"result": {"query": ":facetid:toc:\"db/conf/cluster/cluster2002.bht\"", "status": {"@code": "200", "text": "OK"}, "time": {"@unit": "msecs", "text": "190.19"}, "completions": {"@total": "1", "@computed": "1", "@sent": "1", "c": {"@sc": "69", "@dc": "69", "@oc": "69", "@id": "40538028", "text": ":facetid:toc:db/conf/cluster/cluster2002.bht"}}, "hits": {"@total": "69", "@computed": "69", "@sent": "69", "@first": "0", "hit": [{"@score": "1", "@id": "5884248", "info": {"authors": {"author": [{"@pid": "00/4055", "text": "Jameela Al-Jaroodi"}, {"@pid": "04/2984", "text": "Nader Mohamed"}, {"@pid": "16/3631-1", "text": "Hong Jiang 0001"}, {"@pid": "86/1666", "text": "David R. Swanson"}]}, "title": "An Agent-Based Infrastructure for Parallel Java on Heterogeneous Cluster.", "venue": "CLUSTER", "pages": "19-27", "year": "2002", "type": "Conference and Workshop Papers", "access": "closed", "key": "conf/cluster/Al-JaroodiMJS02", "doi": "10.1109/CLUSTR.2002.1137724", "ee": "https://doi.org/10.1109/CLUSTR.2002.1137724", "url": "https://dblp.org/rec/conf/cluster/Al-JaroodiMJS02"}, "url": "URL#5884248"}, {"@score": "1", "@id": "5884249", "info": {"authors": {"author": [{"@pid": "65/2523", "text": "Yuri Alexeev"}, {"@pid": "56/567", "text": "Michael W. Schmidt"}, {"@pid": "92/3874", "text": "Theresa L. Windus"}, {"@pid": "76/6591", "text": "Mark S. Gordon"}, {"@pid": "k/RAKendall", "text": "Ricky A. Kendall"}]}, "title": "Performance and Implementation of Distributed Data CPHF and SCF Algorithms.", "venue": "CLUSTER", "pages": "135-", "year": "2002", "type": "Conference and Workshop Papers", "access": "closed", "key": "conf/cluster/AlexeevSWGK02", "doi": "10.1109/CLUSTR.2002.1137738", "ee": "https://doi.org/10.1109/CLUSTR.2002.1137738", "url": "https://dblp.org/rec/conf/cluster/AlexeevSWGK02"}, "url": "URL#5884249"}, {"@score": "1", "@id": "5884250", "info": {"authors": {"author": [{"@pid": "a/GeorgeAlmasi2", "text": "George S. Alm\u00e1si"}, {"@pid": "75/3148", "text": "Daniel K. Beece"}, {"@pid": "57/4005", "text": "Ralph Bellofatto"}, {"@pid": "93/1730", "text": "Gyan Bhanot"}, {"@pid": "26/1329", "text": "Randy Bickford"}, {"@pid": "85/2383", "text": "Matthias A. Blumrich"}, {"@pid": "85/5663", "text": "Arthur A. Bright"}, {"@pid": "03/1537", "text": "Jos\u00e9 R. Brunheroto"}, {"@pid": "c/CalinCascaval", "text": "Calin Cascaval"}, {"@pid": "74/2394", "text": "Jos\u00e9 G. Casta\u00f1os"}, {"@pid": "95/5263", "text": "Luis Ceze"}, {"@pid": "49/2699", "text": "Paul Coteus"}, {"@pid": "c/SiddharthaChatterjee", "text": "Siddhartha Chatterjee"}, {"@pid": "44/3371-5", "text": "Dong Chen 0005"}, {"@pid": "80/6030", "text": "George L.-T. Chiu"}, {"@pid": "64/365", "text": "Thomas M. Cipolla"}, {"@pid": "23/1938", "text": "Paul Crumley"}, {"@pid": "27/1240", "text": "Alina Deutsch"}, {"@pid": "25/2736", "text": "Marc Boris Dombrowa"}, {"@pid": "48/5892", "text": "Wilm E. Donath"}, {"@pid": "46/3306", "text": "Maria Eleftheriou"}, {"@pid": "33/3443", "text": "Blake G. Fitch"}, {"@pid": "55/5859", "text": "Joseph Gagliano"}, {"@pid": "81/606", "text": "Alan Gara"}, {"@pid": "89/3437", "text": "Robert S. Germain"}, {"@pid": "21/3386", "text": "Mark Giampapa"}, {"@pid": "g/ManishGupta2", "text": "Manish Gupta 0002"}, {"@pid": "29/6667", "text": "Fred G. Gustavson"}, {"@pid": "64/1162", "text": "Shawn Hall"}, {"@pid": "98/810", "text": "Ruud A. Haring"}, {"@pid": "64/6773", "text": "David F. Heidel"}, {"@pid": "h/PhilipHeidelberger", "text": "Philip Heidelberger"}, {"@pid": "152/9447", "text": "Lorraine Herger"}, {"@pid": "53/3548", "text": "Dirk Hoenicke"}, {"@pid": "74/3512", "text": "T. Jamal-Eddine"}, {"@pid": "16/3845", "text": "Gerard V. Kopcsay"}, {"@pid": "69/3655", "text": "Alphonso P. Lanzetta"}, {"@pid": "69/4167", "text": "Derek Lieber"}, {"@pid": "60/3371", "text": "M. Lu"}, {"@pid": "93/4413", "text": "Mark P. Mendell"}, {"@pid": "27/3150", "text": "Lawrence S. Mok"}, {"@pid": "12/1593", "text": "Jos\u00e9 E. Moreira"}, {"@pid": "65/4783", "text": "Ben J. Nathanson"}, {"@pid": "62/416", "text": "Matthew Newton"}, {"@pid": "72/6058", "text": "Martin Ohmacht"}, {"@pid": "66/1895", "text": "Rick A. Rand"}, {"@pid": "22/1342", "text": "Richard D. Regan"}, {"@pid": "99/4767", "text": "Ramendra K. Sahoo"}, {"@pid": "94/5880", "text": "Alda Sanomiya"}, {"@pid": "36/2777", "text": "Eugen Schenfeld"}, {"@pid": "16/3925", "text": "Sarabjeet Singh"}, {"@pid": "18/1025", "text": "Peilin Song"}, {"@pid": "77/5301", "text": "Burkhard D. Steinmacher-Burow"}, {"@pid": "60/4729", "text": "Karin Strauss"}, {"@pid": "77/5322", "text": "Richard A. Swetz"}, {"@pid": "80/3641", "text": "Todd Takken"}, {"@pid": "69/2128", "text": "R. Brett Tremaine"}, {"@pid": "44/4696", "text": "Mickey Tsao"}, {"@pid": "36/1794", "text": "Pavlos Vranas"}, {"@pid": "15/1189", "text": "T. J. Christopher Ward"}, {"@pid": "92/4149", "text": "Michael E. Wazlowski"}, {"@pid": "05/3444", "text": "J. Brown"}, {"@pid": "36/1235", "text": "Thomas A. Liebsch"}, {"@pid": "82/1724", "text": "A. Schram"}, {"@pid": "49/2269", "text": "G. Ulsh"}]}, "title": "Blue Gene/L, a System-On-A-Chip.", "venue": "CLUSTER", "pages": "349-", "year": "2002", "type": "Conference and Workshop Papers", "access": "closed", "key": "conf/cluster/AlmasiAB02", "doi": "10.1109/CLUSTR.2002.1137766", "ee": "https://doi.org/10.1109/CLUSTR.2002.1137766", "url": "https://dblp.org/rec/conf/cluster/AlmasiAB02"}, "url": "URL#5884250"}, {"@score": "1", "@id": "5884251", "info": {"authors": {"author": [{"@pid": "70/2491", "text": "Pavan Balaji"}, {"@pid": "62/3546", "text": "Piyush Shivam"}, {"@pid": "159/1483", "text": "Pete Wyckoff"}, {"@pid": "p/DhabaleswarKPanda", "text": "Dhabaleswar K. Panda 0001"}]}, "title": "High Performance User Level Sockets over Gigabit Ethernet.", "venue": "CLUSTER", "pages": "179-186", "year": "2002", "type": "Conference and Workshop Papers", "access": "closed", "key": "conf/cluster/BalajiSWP02", "doi": "10.1109/CLUSTR.2002.1137745", "ee": "https://doi.org/10.1109/CLUSTR.2002.1137745", "url": "https://dblp.org/rec/conf/cluster/BalajiSWP02"}, "url": "URL#5884251"}, {"@score": "1", "@id": "5884252", "info": {"authors": {"author": [{"@pid": "91/268", "text": "Win Bausch"}, {"@pid": "p/CesarePautasso", "text": "Cesare Pautasso"}, {"@pid": "12/951", "text": "Reto Schaeppi"}, {"@pid": "a/GustavoAlonso", "text": "Gustavo Alonso"}]}, "title": "BioOpera: Cluster-Aware Computing.", "venue": "CLUSTER", "pages": "99-106", "year": "2002", "type": "Conference and Workshop Papers", "access": "closed", "key": "conf/cluster/BauschPSA02", "doi": "10.1109/CLUSTR.2002.1137734", "ee": "https://doi.org/10.1109/CLUSTR.2002.1137734", "url": "https://dblp.org/rec/conf/cluster/BauschPSA02"}, "url": "URL#5884252"}, {"@score": "1", "@id": "5884253", "info": {"authors": {"author": [{"@pid": "72/1526", "text": "Michael D. Beynon"}, {"@pid": "a/HAndrade", "text": "Henrique Andrade"}, {"@pid": "s/JoelHSaltz", "text": "Joel H. Saltz"}]}, "title": "Low-Cost Non-Intrusive Debugging Strategies for Distributed Parallel Programs.", "venue": "CLUSTER", "pages": "439-442", "year": "2002", "type": "Conference and Workshop Papers", "access": "closed", "key": "conf/cluster/BeynonAS02", "doi": "10.1109/CLUSTR.2002.1137778", "ee": "https://doi.org/10.1109/CLUSTR.2002.1137778", "url": "https://dblp.org/rec/conf/cluster/BeynonAS02"}, "url": "URL#5884253"}, {"@score": "1", "@id": "5884254", "info": {"authors": {"author": {"@pid": "49/1486", "text": "Brett M. Bode"}}, "title": "Interconnects: Which One Is Right for You?", "venue": "CLUSTER", "pages": "344", "year": "2002", "type": "Conference and Workshop Papers", "access": "closed", "key": "conf/cluster/Bode02", "doi": "10.1109/CLUSTR.2002.1137764", "ee": "https://doi.org/10.1109/CLUSTR.2002.1137764", "url": "https://dblp.org/rec/conf/cluster/Bode02"}, "url": "URL#5884254"}, {"@score": "1", "@id": "5884255", "info": {"authors": {"author": {"@pid": "69/2472", "text": "Pete Bradley"}}, "title": "Production Clustering at Pratt &amp; Whitney: Desktop Supercomputing for Engineering Design.", "venue": "CLUSTER", "pages": "171", "year": "2002", "type": "Conference and Workshop Papers", "access": "closed", "key": "conf/cluster/Bradley02", "doi": "10.1109/CLUSTR.2002.1137742", "ee": "https://doi.org/10.1109/CLUSTR.2002.1137742", "url": "https://dblp.org/rec/conf/cluster/Bradley02"}, "url": "URL#5884255"}, {"@score": "1", "@id": "5884256", "info": {"authors": {"author": {"@pid": "59/1752", "text": "Kirk Bresniker"}}, "title": "Blades - An Emerging System Design Model for Economic Delivery of High Performance Computing.", "venue": "CLUSTER", "pages": "5-", "year": "2002", "type": "Conference and Workshop Papers", "access": "closed", "key": "conf/cluster/Bresnike02", "doi": "10.1109/CLUSTR.2002.1137722", "ee": "https://doi.org/10.1109/CLUSTR.2002.1137722", "url": "https://dblp.org/rec/conf/cluster/Bresnike02"}, "url": "URL#5884256"}, {"@score": "1", "@id": "5884257", "info": {"authors": {"author": {"@pid": "58/170", "text": "Emmanuel Cecchet"}}, "title": "Memory Mapped Networks: A New Deal for Distributed Shared Memories? The SciFS Experience.", "venue": "CLUSTER", "pages": "231-238", "year": "2002", "type": "Conference and Workshop Papers", "access": "closed", "key": "conf/cluster/Cecchet02", "doi": "10.1109/CLUSTR.2002.1137751", "ee": "https://doi.org/10.1109/CLUSTR.2002.1137751", "url": "https://dblp.org/rec/conf/cluster/Cecchet02"}, "url": "URL#5884257"}, {"@score": "1", "@id": "5884258", "info": {"authors": {"author": [{"@pid": "87/1254", "text": "Yu Chen"}, {"@pid": "47/3514", "text": "Xiaoge Wang"}, {"@pid": "85/5039", "text": "Zhenqiang Jiao"}, {"@pid": "33/3881", "text": "Jun Xie"}, {"@pid": "74/6277", "text": "Zhihui Du"}, {"@pid": "54/5095", "text": "Sanli Li"}]}, "title": "MyVIA: A Design and Implementation of the High Performance Virtual Interface Architecture.", "venue": "CLUSTER", "pages": "160-", "year": "2002", "type": "Conference and Workshop Papers", "access": "closed", "key": "conf/cluster/ChenWJXDL02", "doi": "10.1109/CLUSTR.2002.1137741", "ee": "https://doi.org/10.1109/CLUSTR.2002.1137741", "url": "https://dblp.org/rec/conf/cluster/ChenWJXDL02"}, "url": "URL#5884258"}, {"@score": "1", "@id": "5884259", "info": {"authors": {"author": [{"@pid": "97/6329", "text": "Avery Ching"}, {"@pid": "c/AlokNChoudhary", "text": "Alok N. Choudhary"}, {"@pid": "45/1370", "text": "Wei-keng Liao"}, {"@pid": "r/RBRoss", "text": "Robert B. Ross"}, {"@pid": "g/WilliamGropp", "text": "William Gropp"}]}, "title": "Noncontiguous I/O through PVFS.", "venue": "CLUSTER", "pages": "405-414", "year": "2002", "type": "Conference and Workshop Papers", "access": "closed", "key": "conf/cluster/ChingNCLRG02", "doi": "10.1109/CLUSTR.2002.1137773", "ee": "https://doi.org/10.1109/CLUSTR.2002.1137773", "url": "https://dblp.org/rec/conf/cluster/ChingNCLRG02"}, "url": "URL#5884259"}, {"@score": "1", "@id": "5884260", "info": {"authors": {"author": [{"@pid": "69/79", "text": "Anthony T. Chronopoulos"}, {"@pid": "77/757", "text": "Satish Penmatsa"}, {"@pid": "24/3024", "text": "Ning Yu"}]}, "title": "Scalable Loop Self-Scheduling Schemes for Heterogeneous Clusters.", "venue": "CLUSTER", "pages": "353-359", "year": "2002", "type": "Conference and Workshop Papers", "access": "closed", "key": "conf/cluster/ChronopoulosPY02", "doi": "10.1109/CLUSTR.2002.1137767", "ee": "https://doi.org/10.1109/CLUSTR.2002.1137767", "url": "https://dblp.org/rec/conf/cluster/ChronopoulosPY02"}, "url": "URL#5884260"}, {"@score": "1", "@id": "5884261", "info": {"authors": {"author": [{"@pid": "94/3021", "text": "Roxana Diaconescu"}, {"@pid": "c/ReidarConradi", "text": "Reidar Conradi"}]}, "title": "A Data Parallel Programming Model Based on Distributed Objects.", "venue": "CLUSTER", "pages": "455-460", "year": "2002", "type": "Conference and Workshop Papers", "access": "closed", "key": "conf/cluster/DiaconescuC02", "doi": "10.1109/CLUSTR.2002.1137782", "ee": "https://doi.org/10.1109/CLUSTR.2002.1137782", "url": "https://dblp.org/rec/conf/cluster/DiaconescuC02"}, "url": "URL#5884261"}, {"@score": "1", "@id": "5884262", "info": {"authors": {"author": [{"@pid": "40/3662", "text": "Gerardo D\u00edaz-Cu\u00e9llar"}, {"@pid": "89/2936", "text": "David A. Garza-Salazar"}]}, "title": "A Parallelization Technique that Improves Performance and Cluster Utilization Efficiency for Heterogeneous Clusters of Workstations.", "venue": "CLUSTER", "pages": "275-", "year": "2002", "type": "Conference and Workshop Papers", "access": "closed", "key": "conf/cluster/Diaz-CuellarG02", "doi": "10.1109/CLUSTR.2002.1137756", "ee": "https://doi.org/10.1109/CLUSTR.2002.1137756", "url": "https://dblp.org/rec/conf/cluster/Diaz-CuellarG02"}, "url": "URL#5884262"}, {"@score": "1", "@id": "5884263", "info": {"authors": {"author": {"@pid": "d/JackDongarra", "text": "Jack J. Dongarra"}}, "title": "Trends in High Performance Computing and Using Numerical Libraries on Cluster.", "venue": "CLUSTER", "pages": "172-", "year": "2002", "type": "Conference and Workshop Papers", "access": "closed", "key": "conf/cluster/Dongarra02", "doi": "10.1109/CLUSTR.2002.1137743", "ee": "https://doi.org/10.1109/CLUSTR.2002.1137743", "url": "https://dblp.org/rec/conf/cluster/Dongarra02"}, "url": "URL#5884263"}, {"@score": "1", "@id": "5884264", "info": {"authors": {"author": [{"@pid": "62/4528", "text": "R\u00e9my Evard"}, {"@pid": "01/6327", "text": "Narayan Desai"}, {"@pid": "00/5978", "text": "John-Paul Navarro"}, {"@pid": "14/1489", "text": "Daniel Nurmi"}]}, "title": "Clusters as Large-Scale.", "venue": "CLUSTER", "pages": "54-", "year": "2002", "type": "Conference and Workshop Papers", "access": "closed", "key": "conf/cluster/EvardDNN02", "doi": "10.1109/CLUSTR.2002.1137729", "ee": "https://doi.org/10.1109/CLUSTR.2002.1137729", "url": "https://dblp.org/rec/conf/cluster/EvardDNN02"}, "url": "URL#5884264"}, {"@score": "1", "@id": "5884265", "info": {"authors": {"author": [{"@pid": "31/5444", "text": "Thomas Fahringer"}, {"@pid": "87/3268", "text": "Alexandru Jugravu"}, {"@pid": "19/953", "text": "Beniamino Di Martino"}, {"@pid": "66/3823", "text": "Salvatore Venticinque"}, {"@pid": "07/462", "text": "Hans Moritsch"}]}, "title": "On the Evaluation of JavaSymphony for Cluster Applications.", "venue": "CLUSTER", "pages": "394-", "year": "2002", "type": "Conference and Workshop Papers", "access": "closed", "key": "conf/cluster/FahringerJMVM02", "doi": "10.1109/CLUSTR.2002.1137772", "ee": "https://doi.org/10.1109/CLUSTR.2002.1137772", "url": "https://dblp.org/rec/conf/cluster/FahringerJMVM02"}, "url": "URL#5884265"}, {"@score": "1", "@id": "5884266", "info": {"authors": {"author": [{"@pid": "82/6853", "text": "Wu-chun Feng"}, {"@pid": "44/5079", "text": "Michael S. Warren"}, {"@pid": "43/2084", "text": "Eric Weigle"}]}, "title": "The Bladed Beowulf: A Cost-Effective Alternative to Traditional Beowulf.", "venue": "CLUSTER", "pages": "245-", "year": "2002", "type": "Conference and Workshop Papers", "access": "closed", "key": "conf/cluster/FengWW02", "doi": "10.1109/CLUSTR.2002.1137753", "ee": "https://doi.org/10.1109/CLUSTR.2002.1137753", "url": "https://dblp.org/rec/conf/cluster/FengWW02"}, "url": "URL#5884266"}, {"@score": "1", "@id": "5884267", "info": {"authors": {"author": [{"@pid": "90/939", "text": "Eitan Frachtenberg"}, {"@pid": "81/5123", "text": "Fabrizio Petrini"}, {"@pid": "f/JuanFernandezPeinador", "text": "Juan Fern\u00e1ndez 0001"}, {"@pid": "88/2959", "text": "Salvador Coll"}]}, "title": "Scalable Resource Management in High Performance Computers.", "venue": "CLUSTER", "pages": "305-", "year": "2002", "type": "Conference and Workshop Papers", "access": "closed", "key": "conf/cluster/FrachtenbergPFC02", "doi": "10.1109/CLUSTR.2002.1137759", "ee": "https://doi.org/10.1109/CLUSTR.2002.1137759", "url": "https://dblp.org/rec/conf/cluster/FrachtenbergPFC02"}, "url": "URL#5884267"}, {"@score": "1", "@id": "5884268", "info": {"authors": {"author": [{"@pid": "91/1469", "text": "Zhengting Gan"}, {"@pid": "65/2523", "text": "Yuri Alexeev"}, {"@pid": "k/RAKendall", "text": "Ricky A. Kendall"}, {"@pid": "76/6591", "text": "Mark S. Gordon"}]}, "title": "A Distributed Data Implementation of Parallel Full CI Program.", "venue": "CLUSTER", "pages": "476-479", "year": "2002", "type": "Conference and Workshop Papers", "access": "closed", "key": "conf/cluster/GanAKG02", "doi": "10.1109/CLUSTR.2002.1137786", "ee": "https://doi.org/10.1109/CLUSTR.2002.1137786", "url": "https://dblp.org/rec/conf/cluster/GanAKG02"}, "url": "URL#5884268"}, {"@score": "1", "@id": "5884269", "info": {"authors": {"author": [{"@pid": "74/3246", "text": "Georgios I. Goumas"}, {"@pid": "79/2671", "text": "Nikolaos Drosinos"}, {"@pid": "41/1481", "text": "Maria Athanasaki"}, {"@pid": "24/4627", "text": "Nectarios Koziris"}]}, "title": "Compiling Tiled Iteration Spaces for Clusters.", "venue": "CLUSTER", "pages": "360-369", "year": "2002", "type": "Conference and Workshop Papers", "access": "closed", "key": "conf/cluster/GoumasDAK02", "doi": "10.1109/CLUSTR.2002.1137768", "ee": "https://doi.org/10.1109/CLUSTR.2002.1137768", "url": "https://dblp.org/rec/conf/cluster/GoumasDAK02"}, "url": "URL#5884269"}, {"@score": "1", "@id": "5884270", "info": {"authors": {"author": [{"@pid": "g/WilliamGropp", "text": "William Gropp"}, {"@pid": "l/EwingLLusk", "text": "Ewing L. Lusk"}]}, "title": "Goals Guiding Design: PVM and MP.", "venue": "CLUSTER", "pages": "257-265", "year": "2002", "type": "Conference and Workshop Papers", "access": "closed", "key": "conf/cluster/GroppL02", "doi": "10.1109/CLUSTR.2002.1137754", "ee": "https://doi.org/10.1109/CLUSTR.2002.1137754", "url": "https://dblp.org/rec/conf/cluster/GroppL02"}, "url": "URL#5884270"}, {"@score": "1", "@id": "5884271", "info": {"authors": {"author": [{"@pid": "g/DanielGrosu", "text": "Daniel Grosu"}, {"@pid": "69/79", "text": "Anthony T. Chronopoulos"}]}, "title": "Algorithmic Mechanism Design for Load Balancing in Distributed Systems.", "venue": "CLUSTER", "pages": "445-450", "year": "2002", "type": "Conference and Workshop Papers", "access": "closed", "key": "conf/cluster/GrosuC02", "doi": "10.1109/CLUSTR.2002.1137780", "ee": "https://doi.org/10.1109/CLUSTR.2002.1137780", "url": "https://dblp.org/rec/conf/cluster/GrosuC02"}, "url": "URL#5884271"}, {"@score": "1", "@id": "5884272", "info": {"authors": {"author": [{"@pid": "47/4715", "text": "Rinku Gupta"}, {"@pid": "46/1240", "text": "Vinod Tipparaju"}, {"@pid": "53/1812", "text": "Jarek Nieplocha"}, {"@pid": "p/DhabaleswarKPanda", "text": "Dhabaleswar K. Panda 0001"}]}, "title": "Efficient Barrier Using Remote Memory Operations on VIA-Based Clusters.", "venue": "CLUSTER", "pages": "83-", "year": "2002", "type": "Conference and Workshop Papers", "access": "closed", "key": "conf/cluster/GuptaTNP02", "doi": "10.1109/CLUSTR.2002.1137732", "ee": "https://doi.org/10.1109/CLUSTR.2002.1137732", "url": "https://dblp.org/rec/conf/cluster/GuptaTNP02"}, "url": "URL#5884272"}, {"@score": "1", "@id": "5884273", "info": {"authors": {"author": [{"@pid": "43/6755", "text": "J\u00f8rgen S. Hansen"}, {"@pid": "69/1554", "text": "Renaud Lachaiz"}]}, "title": "Using Idle Disks in a Cluster as a High-Performance Storage System.", "venue": "CLUSTER", "pages": "415-424", "year": "2002", "type": "Conference and Workshop Papers", "access": "closed", "key": "conf/cluster/HansenL02", "doi": "10.1109/CLUSTR.2002.1137774", "ee": "https://doi.org/10.1109/CLUSTR.2002.1137774", "url": "https://dblp.org/rec/conf/cluster/HansenL02"}, "url": "URL#5884273"}, {"@score": "1", "@id": "5884274", "info": {"authors": {"author": [{"@pid": "61/2072", "text": "Eric He"}, {"@pid": "29/532", "text": "Jason Leigh"}, {"@pid": "90/1591", "text": "Oliver T. W. Yu"}, {"@pid": "d/ThomasADeFanti", "text": "Thomas A. DeFanti"}]}, "title": "Reliable Blast UDP: Predictable High Performance Bulk Data Transfer.", "venue": "CLUSTER", "pages": "317-324", "year": "2002", "type": "Conference and Workshop Papers", "access": "closed", "key": "conf/cluster/HeLYD02", "doi": "10.1109/CLUSTR.2002.1137760", "ee": "https://doi.org/10.1109/CLUSTR.2002.1137760", "url": "https://dblp.org/rec/conf/cluster/HeLYD02"}, "url": "URL#5884274"}, {"@score": "1", "@id": "5884275", "info": {"authors": {"author": {"@pid": "h/MonikaRauchHenzinger", "text": "Monika Rauch Henzinger"}}, "title": "Indexing the Web - A Challenge for Supercomputers.", "venue": "CLUSTER", "pages": "343", "year": "2002", "type": "Conference and Workshop Papers", "access": "closed", "key": "conf/cluster/Henzinger02", "doi": "10.1109/CLUSTR.2002.1137763", "ee": "https://doi.org/10.1109/CLUSTR.2002.1137763", "url": "https://dblp.org/rec/conf/cluster/Henzinger02"}, "url": "URL#5884275"}, {"@score": "1", "@id": "5884276", "info": {"authors": {"author": [{"@pid": "50/5106", "text": "Chun-Hsi Huang"}, {"@pid": "42/1695", "text": "Ratnabali Biswas"}]}, "title": "Parallel Pattern Identification in Biological Sequences on Clusters.", "venue": "CLUSTER", "pages": "127-134", "year": "2002", "type": "Conference and Workshop Papers", "access": "closed", "key": "conf/cluster/HuangB02", "doi": "10.1109/CLUSTR.2002.1137737", "ee": "https://doi.org/10.1109/CLUSTR.2002.1137737", "url": "https://dblp.org/rec/conf/cluster/HuangB02"}, "url": "URL#5884276"}, {"@score": "1", "@id": "5884277", "info": {"authors": {"author": [{"@pid": "39/4990", "text": "Joon-Hyung Hwangbo"}, {"@pid": "03/471", "text": "Sang-Ki Lee"}, {"@pid": "76/6576", "text": "Yoon-Young Lee"}, {"@pid": "99/5323", "text": "Dae-Wha Seo"}]}, "title": "Adaptive Message Management Using Hybrid Channel Model in Parallel File System.", "venue": "CLUSTER", "pages": "239-244", "year": "2002", "type": "Conference and Workshop Papers", "access": "closed", "key": "conf/cluster/HwangboLLS02", "doi": "10.1109/CLUSTR.2002.1137752", "ee": "https://doi.org/10.1109/CLUSTR.2002.1137752", "url": "https://dblp.org/rec/conf/cluster/HwangboLLS02"}, "url": "URL#5884277"}, {"@score": "1", "@id": "5884278", "info": {"authors": {"author": [{"@pid": "63/5600", "text": "Muhammad Umar Janjua"}, {"@pid": "275/8939", "text": "Muhammad Mehboob Yasin"}, {"@pid": "45/9126", "text": "Ch. Falak Sher"}, {"@pid": "62/2452", "text": "K. Awan"}, {"@pid": "51/3922", "text": "I. Hassan"}]}, "title": "CEJVM: &quot;Cluster Enabled Java Virtual Machine&quot;.", "venue": "CLUSTER", "pages": "389-393", "year": "2002", "type": "Conference and Workshop Papers", "access": "closed", "key": "conf/cluster/JanjuaYSAH02", "doi": "10.1109/CLUSTR.2002.1137771", "ee": "https://doi.org/10.1109/CLUSTR.2002.1137771", "url": "https://dblp.org/rec/conf/cluster/JanjuaYSAH02"}, "url": "URL#5884278"}, {"@score": "1", "@id": "5884279", "info": {"authors": {"author": [{"@pid": "88/6394", "text": "Mason J. Katz"}, {"@pid": "03/3218", "text": "Philip M. Papadopoulos"}, {"@pid": "90/5242", "text": "Greg Bruno"}]}, "title": "Leveraging Standard Core Technologies to Programmatically Build Linux Cluster Appliances.", "venue": "CLUSTER", "pages": "47-53", "year": "2002", "type": "Conference and Workshop Papers", "access": "closed", "key": "conf/cluster/KatzPB02", "doi": "10.1109/CLUSTR.2002.1137728", "ee": "https://doi.org/10.1109/CLUSTR.2002.1137728", "url": "https://dblp.org/rec/conf/cluster/KatzPB02"}, "url": "URL#5884279"}, {"@score": "1", "@id": "5884280", "info": {"authors": {"author": [{"@pid": "47/5980", "text": "James H. Laros III"}, {"@pid": "30/4898", "text": "Lee Ward"}, {"@pid": "26/1574", "text": "Nathan W. Dauchy"}, {"@pid": "78/643", "text": "Ron Brightwell"}, {"@pid": "73/6943", "text": "Trammell Hudson"}, {"@pid": "75/2165", "text": "Ruth Klundt"}]}, "title": "An Extensible, Portable, Scalable Cluster Management Software Architecture.", "venue": "CLUSTER", "pages": "287-295", "year": "2002", "type": "Conference and Workshop Papers", "access": "closed", "key": "conf/cluster/LarosWDBHK02", "doi": "10.1109/CLUSTR.2002.1137757", "ee": "https://doi.org/10.1109/CLUSTR.2002.1137757", "url": "https://dblp.org/rec/conf/cluster/LarosWDBHK02"}, "url": "URL#5884280"}, {"@score": "1", "@id": "5884281", "info": {"authors": {"author": [{"@pid": "11/4142", "text": "William Lawry"}, {"@pid": "68/1623", "text": "Christopher Wilson"}, {"@pid": "m/ArthurBMaccabe", "text": "Arthur B. Maccabe"}, {"@pid": "78/643", "text": "Ron Brightwell"}]}, "title": "COMB: A Portable Benchmark Suite for Assessing MPI Overlap.", "venue": "CLUSTER", "pages": "472-475", "year": "2002", "type": "Conference and Workshop Papers", "access": "closed", "key": "conf/cluster/LawryWMB02", "doi": "10.1109/CLUSTR.2002.1137785", "ee": "https://doi.org/10.1109/CLUSTR.2002.1137785", "url": "https://dblp.org/rec/conf/cluster/LawryWMB02"}, "url": "URL#5884281"}, {"@score": "1", "@id": "5884282", "info": {"authors": {"author": [{"@pid": "24/2952", "text": "Byoung-Dai Lee"}, {"@pid": "52/4225", "text": "Jon B. Weissman"}]}, "title": "Community Services: A Toolkit for Rapid Deployment of Network Services.", "venue": "CLUSTER", "pages": "451-454", "year": "2002", "type": "Conference and Workshop Papers", "access": "closed", "key": "conf/cluster/LeeW02", "doi": "10.1109/CLUSTR.2002.1137781", "ee": "https://doi.org/10.1109/CLUSTR.2002.1137781", "url": "https://dblp.org/rec/conf/cluster/LeeW02"}, "url": "URL#5884282"}, {"@score": "1", "@id": "5884283", "info": {"authors": {"author": [{"@pid": "77/6594", "text": "Vitus J. Leung"}, {"@pid": "46/5034", "text": "Esther M. Arkin"}, {"@pid": "b/MichaelABender", "text": "Michael A. Bender"}, {"@pid": "30/2591", "text": "David P. Bunde"}, {"@pid": "16/4850", "text": "Jeanette Johnston"}, {"@pid": "63/3067", "text": "Alok Lal"}, {"@pid": "m/JosephSBMitchell", "text": "Joseph S. B. Mitchell"}, {"@pid": "18/1807", "text": "Cynthia A. Phillips"}, {"@pid": "16/3941", "text": "Steven S. Seiden"}]}, "title": "Processor Allocation on Cplant: Achieving General Processor Locality Using One-Dimensional Allocation Strategies.", "venue": "CLUSTER", "pages": "296-304", "year": "2002", "type": "Conference and Workshop Papers", "access": "closed", "key": "conf/cluster/LeungABBJLMPS02", "doi": "10.1109/CLUSTR.2002.1137758", "ee": "https://doi.org/10.1109/CLUSTR.2002.1137758", "url": "https://dblp.org/rec/conf/cluster/LeungABBJLMPS02"}, "url": "URL#5884283"}, {"@score": "1", "@id": "5884284", "info": {"authors": {"author": [{"@pid": "47/2372", "text": "Jianwei Li"}, {"@pid": "45/1370", "text": "Wei-keng Liao"}, {"@pid": "c/AlokNChoudhary", "text": "Alok N. Choudhary"}, {"@pid": "50/1380", "text": "Valerie E. Taylor"}]}, "title": "I/O Analysis and Optimization for an AMR Cosmology Application.", "venue": "CLUSTER", "pages": "119-126", "year": "2002", "type": "Conference and Workshop Papers", "access": "closed", "key": "conf/cluster/LiLCT02", "doi": "10.1109/CLUSTR.2002.1137736", "ee": "https://doi.org/10.1109/CLUSTR.2002.1137736", "url": "https://dblp.org/rec/conf/cluster/LiLCT02"}, "url": "URL#5884284"}, {"@score": "1", "@id": "5884285", "info": {"authors": {"author": [{"@pid": "l/MingLi20", "text": "Ming Li 0020"}, {"@pid": "18/5939", "text": "Wenchao Tao"}, {"@pid": "38/6987", "text": "Daniel Goldberg 0002"}, {"@pid": "45/3915", "text": "Israel Hsu"}, {"@pid": "02/4293", "text": "Yuval Tamir"}]}, "title": "Design and Validation of Portable Communication Infrastructure for Fault-Tolerant Cluster Middleware.", "venue": "CLUSTER", "pages": "266-274", "year": "2002", "type": "Conference and Workshop Papers", "access": "closed", "key": "conf/cluster/LiTGHT02", "doi": "10.1109/CLUSTR.2002.1137755", "ee": "https://doi.org/10.1109/CLUSTR.2002.1137755", "url": "https://dblp.org/rec/conf/cluster/LiTGHT02"}, "url": "URL#5884285"}, {"@score": "1", "@id": "5884286", "info": {"authors": {"author": {"@pid": "11/2328", "text": "Walter B. Ligon III"}}, "title": "Research Directions in Parallel I/O for Clusters.", "venue": "CLUSTER", "pages": "436-", "year": "2002", "type": "Conference and Workshop Papers", "access": "closed", "key": "conf/cluster/Ligon02", "doi": "10.1109/CLUSTR.2002.1137777", "ee": "https://doi.org/10.1109/CLUSTR.2002.1137777", "url": "https://dblp.org/rec/conf/cluster/Ligon02"}, "url": "URL#5884286"}, {"@score": "1", "@id": "5884287", "info": {"authors": {"author": [{"@pid": "l/VMLo", "text": "Virginia Mary Lo"}, {"@pid": "m/JensMache", "text": "Jens Mache"}]}, "title": "Job Scheduling for Prime Time vs. Non-Prime Time.", "venue": "CLUSTER", "pages": "488-493", "year": "2002", "type": "Conference and Workshop Papers", "access": "closed", "key": "conf/cluster/LoM02", "doi": "10.1109/CLUSTR.2002.1137789", "ee": "https://doi.org/10.1109/CLUSTR.2002.1137789", "url": "https://dblp.org/rec/conf/cluster/LoM02"}, "url": "URL#5884287"}, {"@score": "1", "@id": "5884288", "info": {"authors": {"author": {"@pid": "l/EwingLLusk", "text": "Ewing L. Lusk"}}, "title": "MPI in 2002: Has it Been Ten Years Already?", "venue": "CLUSTER", "pages": "435", "year": "2002", "type": "Conference and Workshop Papers", "access": "closed", "key": "conf/cluster/Lusk02", "doi": "10.1109/CLUSTR.2002.1137776", "ee": "https://doi.org/10.1109/CLUSTR.2002.1137776", "url": "https://dblp.org/rec/conf/cluster/Lusk02"}, "url": "URL#5884288"}, {"@score": "1", "@id": "5884289", "info": {"authors": {"author": [{"@pid": "m/ArthurBMaccabe", "text": "Arthur B. Maccabe"}, {"@pid": "75/905", "text": "Wenbin Zhu"}, {"@pid": "77/4986", "text": "Jim Otto"}, {"@pid": "r/RolfRiesen", "text": "Rolf Riesen"}]}, "title": "Experience in Offloading Protocol Processing to a Programmable NIC.", "venue": "CLUSTER", "pages": "67-74", "year": "2002", "type": "Conference and Workshop Papers", "access": "closed", "key": "conf/cluster/MaccabeZOR02", "doi": "10.1109/CLUSTR.2002.1137730", "ee": "https://doi.org/10.1109/CLUSTR.2002.1137730", "url": "https://dblp.org/rec/conf/cluster/MaccabeZOR02"}, "url": "URL#5884289"}, {"@score": "1", "@id": "5884290", "info": {"authors": {"author": [{"@pid": "68/4032", "text": "M. T. McMahon"}, {"@pid": "35/4589", "text": "B. P. DeLong"}, {"@pid": "28/6079", "text": "M. E. Fotta"}, {"@pid": "96/3014", "text": "G. J. Weinstock"}, {"@pid": "46/2810", "text": "A. E. Williams"}]}, "title": "MAGE- A Metacomputing Environment for Parallel Program Development on Cluster Computers.", "venue": "CLUSTER", "pages": "467-471", "year": "2002", "type": "Conference and Workshop Papers", "access": "closed", "key": "conf/cluster/McMahonDFWW02", "doi": "10.1109/CLUSTR.2002.1137784", "ee": "https://doi.org/10.1109/CLUSTR.2002.1137784", "url": "https://dblp.org/rec/conf/cluster/McMahonDFWW02"}, "url": "URL#5884290"}, {"@score": "1", "@id": "5884291", "info": {"authors": {"author": [{"@pid": "00/5978", "text": "John-Paul Navarro"}, {"@pid": "62/4528", "text": "R\u00e9my Evard"}, {"@pid": "14/1489", "text": "Daniel Nurmi"}, {"@pid": "01/6327", "text": "Narayan Desai"}]}, "title": "Scalable Cluster Administration - Chiba City I Approach and Lessons Learned.", "venue": "CLUSTER", "pages": "215-221", "year": "2002", "type": "Conference and Workshop Papers", "access": "closed", "key": "conf/cluster/NavarroEND02", "doi": "10.1109/CLUSTR.2002.1137749", "ee": "https://doi.org/10.1109/CLUSTR.2002.1137749", "url": "https://dblp.org/rec/conf/cluster/NavarroEND02"}, "url": "URL#5884291"}, {"@score": "1", "@id": "5884292", "info": {"authors": {"author": [{"@pid": "55/1595", "text": "Soo-Cheol Oh"}, {"@pid": "46/10274", "text": "Sang-Hwa Chung"}, {"@pid": "18/3017", "text": "Hankook Jang"}]}, "title": "Design and Implementation of CC-NUMA Card II for SCI-Based PC Clustering.", "venue": "CLUSTER", "pages": "145-151", "year": "2002", "type": "Conference and Workshop Papers", "access": "closed", "key": "conf/cluster/OhCJ02", "doi": "10.1109/CLUSTR.2002.1137739", "ee": "https://doi.org/10.1109/CLUSTR.2002.1137739", "url": "https://dblp.org/rec/conf/cluster/OhCJ02"}, "url": "URL#5884292"}, {"@score": "1", "@id": "5884293", "info": {"authors": {"author": [{"@pid": "91/1284", "text": "Kevin T. Pedretti"}, {"@pid": "78/643", "text": "Ron Brightwell"}, {"@pid": "68/3445", "text": "Joshua Williams"}]}, "title": "Cplant? Runtime System Support for Multi-Processor and Heterogeneous Compute Nodes.", "venue": "CLUSTER", "pages": "207-214", "year": "2002", "type": "Conference and Workshop Papers", "access": "closed", "key": "conf/cluster/PedrettiBW02", "doi": "10.1109/CLUSTR.2002.1137748", "ee": "https://doi.org/10.1109/CLUSTR.2002.1137748", "url": "https://dblp.org/rec/conf/cluster/PedrettiBW02"}, "url": "URL#5884293"}, {"@score": "1", "@id": "5884294", "info": {"authors": {"author": [{"@pid": "38/1142", "text": "Liang Peng"}, {"@pid": "37/1143", "text": "Weng-Fai Wong"}, {"@pid": "62/6631", "text": "Chung-Kwong Yuen"}]}, "title": "SilkRoad II: A Multi-Paradigm Runtime System for Cluster Computing.", "venue": "CLUSTER", "pages": "443-444", "year": "2002", "type": "Conference and Workshop Papers", "access": "closed", "key": "conf/cluster/PengWY02", "doi": "10.1109/CLUSTR.2002.1137779", "ee": "https://doi.org/10.1109/CLUSTR.2002.1137779", "url": "https://dblp.org/rec/conf/cluster/PengWY02"}, "url": "URL#5884294"}, {"@score": "1", "@id": "5884295", "info": {"authors": {"author": [{"@pid": "22/3167", "text": "Makan Pourzandi"}, {"@pid": "00/5534", "text": "Ibrahim Haddad"}, {"@pid": "14/6518", "text": "Charles Levert"}, {"@pid": "13/1685", "text": "Miroslaw Zakrzewski"}, {"@pid": "308/1174", "text": "Michel Dagenais"}]}, "title": "A New Architecture for Secure Carrier-Class Clusters.", "venue": "CLUSTER", "pages": "494-498", "year": "2002", "type": "Conference and Workshop Papers", "access": "closed", "key": "conf/cluster/PourzandiHLZD02", "doi": "10.1109/CLUSTR.2002.1137790", "ee": "https://doi.org/10.1109/CLUSTR.2002.1137790", "url": "https://dblp.org/rec/conf/cluster/PourzandiHLZD02"}, "url": "URL#5884295"}, {"@score": "1", "@id": "5884296", "info": {"authors": {"author": [{"@pid": "43/1754", "text": "Radu Prodan"}, {"@pid": "31/5444", "text": "Thomas Fahringer"}]}, "title": "ZENTURIO: An Experiment Management System for Cluster and Grid Computing.", "venue": "CLUSTER", "pages": "9-18", "year": "2002", "type": "Conference and Workshop Papers", "access": "closed", "key": "conf/cluster/ProdanF02", "doi": "10.1109/CLUSTR.2002.1137723", "ee": "https://doi.org/10.1109/CLUSTR.2002.1137723", "url": "https://dblp.org/rec/conf/cluster/ProdanF02"}, "url": "URL#5884296"}, {"@score": "1", "@id": "5884297", "info": {"authors": {"author": {"@pid": "91/1927-2", "text": "Bruno Richard 0002"}}, "title": "I-Cluster: The Execution Sandbox.", "venue": "CLUSTER", "pages": "93-98", "year": "2002", "type": "Conference and Workshop Papers", "access": "closed", "key": "conf/cluster/Richard02", "doi": "10.1109/CLUSTR.2002.1137733", "ee": "https://doi.org/10.1109/CLUSTR.2002.1137733", "url": "https://dblp.org/rec/conf/cluster/Richard02"}, "url": "URL#5884297"}, {"@score": "1", "@id": "5884298", "info": {"authors": {"author": [{"@pid": "89/2040", "text": "Erich Schikuta"}, {"@pid": "03/6272", "text": "Peter Kirkovits"}]}, "title": "Cluster Based Hybrid Hash Join: Analysis and Evaluation.", "venue": "CLUSTER", "pages": "461-466", "year": "2002", "type": "Conference and Workshop Papers", "access": "closed", "key": "conf/cluster/SchikutaK02", "doi": "10.1109/CLUSTR.2002.1137783", "ee": "https://doi.org/10.1109/CLUSTR.2002.1137783", "url": "https://dblp.org/rec/conf/cluster/SchikutaK02"}, "url": "URL#5884298"}, {"@score": "1", "@id": "5884299", "info": {"authors": {"author": [{"@pid": "53/6242", "text": "Jeff Siegel"}, {"@pid": "87/289", "text": "Paul Lu"}]}, "title": "User-Level Remote Data Access in Overlay Metacomputers.", "venue": "CLUSTER", "pages": "480-483", "year": "2002", "type": "Conference and Workshop Papers", "access": "closed", "key": "conf/cluster/SiegelL02", "doi": "10.1109/CLUSTR.2002.1137787", "ee": "https://doi.org/10.1109/CLUSTR.2002.1137787", "url": "https://dblp.org/rec/conf/cluster/SiegelL02"}, "url": "URL#5884299"}, {"@score": "1", "@id": "5884300", "info": {"authors": {"author": [{"@pid": "78/6287", "text": "Steve Sistare"}, {"@pid": "97/2055", "text": "Jack Test"}, {"@pid": "96/4135", "text": "Dave Plauger"}]}, "title": "An Architecture for Integrated Resource Management of MPI Jobs.", "venue": "CLUSTER", "pages": "370-", "year": "2002", "type": "Conference and Workshop Papers", "access": "closed", "key": "conf/cluster/SistareTP02", "doi": "10.1109/CLUSTR.2002.1137769", "ee": "https://doi.org/10.1109/CLUSTR.2002.1137769", "url": "https://dblp.org/rec/conf/cluster/SistareTP02"}, "url": "URL#5884300"}, {"@score": "1", "@id": "5884301", "info": {"authors": {"author": [{"@pid": "11/553", "text": "Yiu-Fai Sit"}, {"@pid": "44/3271", "text": "Cho-Li Wang"}, {"@pid": "l/FrancisChiMoonLau", "text": "Francis C. M. Lau 0001"}]}, "title": "Socket Cloning for Cluster-Based Web Servers.", "venue": "CLUSTER", "pages": "333-", "year": "2002", "type": "Conference and Workshop Papers", "access": "closed", "key": "conf/cluster/SitWL02", "doi": "10.1109/CLUSTR.2002.1137762", "ee": "https://doi.org/10.1109/CLUSTR.2002.1137762", "url": "https://dblp.org/rec/conf/cluster/SitWL02"}, "url": "URL#5884301"}, {"@score": "1", "@id": "5884302", "info": {"authors": {"author": [{"@pid": "92/4097", "text": "Matthew J. Sottile"}, {"@pid": "m/RonaldMinnich", "text": "Ronald G. Minnich"}]}, "title": "Supermon: A High-Speed Cluster Monitoring System.", "venue": "CLUSTER", "pages": "39-46", "year": "2002", "type": "Conference and Workshop Papers", "access": "closed", "key": "conf/cluster/SottileM02", "doi": "10.1109/CLUSTR.2002.1137727", "ee": "https://doi.org/10.1109/CLUSTR.2002.1137727", "url": "https://dblp.org/rec/conf/cluster/SottileM02"}, "url": "URL#5884302"}, {"@score": "1", "@id": "5884303", "info": {"authors": {"author": {"@pid": "34/2635", "text": "Thomas L. Sterling"}}, "title": "Launching into the Future of Commodity Cluster Computing.", "venue": "CLUSTER", "pages": "345-", "year": "2002", "type": "Conference and Workshop Papers", "access": "closed", "key": "conf/cluster/Sterling02", "doi": "10.1109/CLUSTR.2002.1137765", "ee": "https://doi.org/10.1109/CLUSTR.2002.1137765", "url": "https://dblp.org/rec/conf/cluster/Sterling02"}, "url": "URL#5884303"}, {"@score": "1", "@id": "5884304", "info": {"authors": {"author": [{"@pid": "64/1497", "text": "Vijay Subramani"}, {"@pid": "93/756", "text": "Rajkumar Kettimuthu"}, {"@pid": "61/4739", "text": "Srividya Srinivasan"}, {"@pid": "16/4850", "text": "Jeanette Johnston"}, {"@pid": "s/PSadayappan", "text": "P. Sadayappan"}]}, "title": "Selective Buddy Allocation for Scheduling Parallel Jobs on Clusters.", "venue": "CLUSTER", "pages": "107-", "year": "2002", "type": "Conference and Workshop Papers", "access": "closed", "key": "conf/cluster/SubramaniKSJS02", "doi": "10.1109/CLUSTR.2002.1137735", "ee": "https://doi.org/10.1109/CLUSTR.2002.1137735", "url": "https://dblp.org/rec/conf/cluster/SubramaniKSJS02"}, "url": "URL#5884304"}, {"@score": "1", "@id": "5884305", "info": {"authors": {"author": [{"@pid": "58/4337", "text": "C. M. Tan"}, {"@pid": "38/5362", "text": "C. P. Tan"}, {"@pid": "37/1143", "text": "Weng-Fai Wong"}]}, "title": "Shell over a Cluster (SHOC): Towards Achieving Single System Image via the Shell.", "venue": "CLUSTER", "pages": "28-", "year": "2002", "type": "Conference and Workshop Papers", "access": "closed", "key": "conf/cluster/TanTW02", "doi": "10.1109/CLUSTR.2002.1137725", "ee": "https://doi.org/10.1109/CLUSTR.2002.1137725", "url": "https://dblp.org/rec/conf/cluster/TanTW02"}, "url": "URL#5884305"}, {"@score": "1", "@id": "5884306", "info": {"authors": {"author": [{"@pid": "96/3807", "text": "Keiji Tani"}, {"@pid": "05/3528", "text": "Takayuki Aoki"}, {"@pid": "57/4464", "text": "Satoshi Matsuoka"}, {"@pid": "44/4492", "text": "Satoru Ohkura"}, {"@pid": "40/1863", "text": "Hitoshi Uehara"}, {"@pid": "74/337", "text": "Tetsuo Aoyagi"}]}, "title": "First Light of the Earth Simulator and Its PC Cluster Applications.", "venue": "CLUSTER", "pages": "175-", "year": "2002", "type": "Conference and Workshop Papers", "access": "closed", "key": "conf/cluster/TaniAMOUA02", "doi": "10.1109/CLUSTR.2002.1137744", "ee": "https://doi.org/10.1109/CLUSTR.2002.1137744", "url": "https://dblp.org/rec/conf/cluster/TaniAMOUA02"}, "url": "URL#5884306"}, {"@score": "1", "@id": "5884307", "info": {"authors": {"author": [{"@pid": "30/888", "text": "Filip De Turck"}, {"@pid": "58/6169", "text": "Stefaan Vanhastel"}, {"@pid": "57/6011", "text": "Pieter Thysebaert"}, {"@pid": "56/3545", "text": "Bruno Volckaert"}, {"@pid": "d/PietDemeester", "text": "Piet Demeester"}, {"@pid": "39/211", "text": "Bart Dhoedt"}]}, "title": "Design of a Middleware-Based Cluster Management Platform with Task Management and Migration.", "venue": "CLUSTER", "pages": "484-487", "year": "2002", "type": "Conference and Workshop Papers", "access": "closed", "key": "conf/cluster/TurckVTVDD02", "doi": "10.1109/CLUSTR.2002.1137788", "ee": "https://doi.org/10.1109/CLUSTR.2002.1137788", "url": "https://dblp.org/rec/conf/cluster/TurckVTVDD02"}, "url": "URL#5884307"}, {"@score": "1", "@id": "5884308", "info": {"authors": {"author": [{"@pid": "10/3736", "text": "Dave Turner"}, {"@pid": "08/2198", "text": "Xuehua Chen"}]}, "title": "Protocol-Dependent Message-Passing Performance on Linux Clusters.", "venue": "CLUSTER", "pages": "187-194", "year": "2002", "type": "Conference and Workshop Papers", "access": "closed", "key": "conf/cluster/TurnerC02", "doi": "10.1109/CLUSTR.2002.1137746", "ee": "https://doi.org/10.1109/CLUSTR.2002.1137746", "url": "https://dblp.org/rec/conf/cluster/TurnerC02"}, "url": "URL#5884308"}, {"@score": "1", "@id": "5884309", "info": {"authors": {"author": [{"@pid": "91/1438", "text": "Murali Vilayannur"}, {"@pid": "k/MahmutTKandemir", "text": "Mahmut T. Kandemir"}, {"@pid": "72/3356", "text": "Anand Sivasubramaniam"}]}, "title": "Kernel-Level Caching for Optimizing I/O by Exploiting Inter-Application Data Sharing.", "venue": "CLUSTER", "pages": "425-", "year": "2002", "type": "Conference and Workshop Papers", "access": "closed", "key": "conf/cluster/VilayannurKS02", "doi": "10.1109/CLUSTR.2002.1137775", "ee": "https://doi.org/10.1109/CLUSTR.2002.1137775", "url": "https://dblp.org/rec/conf/cluster/VilayannurKS02"}, "url": "URL#5884309"}, {"@score": "1", "@id": "5884310", "info": {"authors": {"author": [{"@pid": "26/3401", "text": "Richard S. Wilkins"}, {"@pid": "85/648", "text": "Xing Du"}, {"@pid": "37/4019", "text": "Robert A. Cochran"}, {"@pid": "95/2186", "text": "Matthias Popp"}]}, "title": "Disaster Tolerant Wolfpack Geo-Clusters.", "venue": "CLUSTER", "pages": "222-", "year": "2002", "type": "Conference and Workshop Papers", "access": "closed", "key": "conf/cluster/WilkinsDCP02", "doi": "10.1109/CLUSTR.2002.1137750", "ee": "https://doi.org/10.1109/CLUSTR.2002.1137750", "url": "https://dblp.org/rec/conf/cluster/WilkinsDCP02"}, "url": "URL#5884310"}, {"@score": "1", "@id": "5884311", "info": {"authors": {"author": [{"@pid": "17/5713", "text": "Meng-Shiou Wu"}, {"@pid": "a/SAluru", "text": "Srinivas Aluru"}, {"@pid": "k/RAKendall", "text": "Ricky A. Kendall"}]}, "title": "Mixed Mode Matrix Multiplication.", "venue": "CLUSTER", "pages": "195-", "year": "2002", "type": "Conference and Workshop Papers", "access": "closed", "key": "conf/cluster/WuAK02", "doi": "10.1109/CLUSTR.2002.1137747", "ee": "https://doi.org/10.1109/CLUSTR.2002.1137747", "url": "https://dblp.org/rec/conf/cluster/WuAK02"}, "url": "URL#5884311"}, {"@score": "1", "@id": "5884312", "info": {"authors": {"author": [{"@pid": "64/2146", "text": "Jiesheng Wu"}, {"@pid": "74/264", "text": "Jiuxing Liu"}, {"@pid": "159/1483", "text": "Pete Wyckoff"}, {"@pid": "p/DhabaleswarKPanda", "text": "Dhabaleswar K. Panda 0001"}]}, "title": "Impact of On-Demand Connection Management in MPI over VIA.", "venue": "CLUSTER", "pages": "152-159", "year": "2002", "type": "Conference and Workshop Papers", "access": "closed", "key": "conf/cluster/WuLWP02", "doi": "10.1109/CLUSTR.2002.1137740", "ee": "https://doi.org/10.1109/CLUSTR.2002.1137740", "url": "https://dblp.org/rec/conf/cluster/WuLWP02"}, "url": "URL#5884312"}, {"@score": "1", "@id": "5884313", "info": {"authors": {"author": [{"@pid": "72/2098", "text": "Ki Hwan Yum"}, {"@pid": "87/5080-1", "text": "Eun Jung Kim 0001"}, {"@pid": "d/ChitaRDas", "text": "Chita R. Das"}, {"@pid": "70/6475", "text": "Mazin S. Yousif"}, {"@pid": "76/2766", "text": "Jos\u00e9 Duato"}]}, "title": "Integrated Admission and Congestion Control for QoS Support in Clusters.", "venue": "CLUSTER", "pages": "325-332", "year": "2002", "type": "Conference and Workshop Papers", "access": "closed", "key": "conf/cluster/YumKDYD02", "doi": "10.1109/CLUSTR.2002.1137761", "ee": "https://doi.org/10.1109/CLUSTR.2002.1137761", "url": "https://dblp.org/rec/conf/cluster/YumKDYD02"}, "url": "URL#5884313"}, {"@score": "1", "@id": "5884314", "info": {"authors": {"author": [{"@pid": "95/873", "text": "Qianfeng Zhang"}, {"@pid": "01/3590", "text": "Chamath Keppitiyagama"}, {"@pid": "09/4049", "text": "Alan S. Wagner"}]}, "title": "Supporting MPI Collective Communication on Network Processors.", "venue": "CLUSTER", "pages": "75-82", "year": "2002", "type": "Conference and Workshop Papers", "access": "closed", "key": "conf/cluster/ZhangKW02", "doi": "10.1109/CLUSTR.2002.1137731", "ee": "https://doi.org/10.1109/CLUSTR.2002.1137731", "url": "https://dblp.org/rec/conf/cluster/ZhangKW02"}, "url": "URL#5884314"}, {"@score": "1", "@id": "5884315", "info": {"authors": {"author": [{"@pid": "42/5225", "text": "Wenzhang Zhu"}, {"@pid": "44/3271", "text": "Cho-Li Wang"}, {"@pid": "l/FrancisChiMoonLau", "text": "Francis C. M. Lau 0001"}]}, "title": "JESSICA2: A Distributed Java Virtual Machine with Transparent Thread Migration Support.", "venue": "CLUSTER", "pages": "381-388", "year": "2002", "type": "Conference and Workshop Papers", "access": "closed", "key": "conf/cluster/ZhuWL02", "doi": "10.1109/CLUSTR.2002.1137770", "ee": "https://doi.org/10.1109/CLUSTR.2002.1137770", "url": "https://dblp.org/rec/conf/cluster/ZhuWL02"}, "url": "URL#5884315"}, {"@score": "1", "@id": "5931584", "info": {"title": "2002 IEEE International Conference on Cluster Computing (CLUSTER 2002), 23-26 September 2002, Chicago, IL, USA", "venue": "CLUSTER", "publisher": "IEEE Computer Society", "year": "2002", "type": "Editorship", "key": "conf/cluster/2002", "ee": "https://ieeexplore.ieee.org/xpl/conhome/8231/proceeding", "url": "https://dblp.org/rec/conf/cluster/2002"}, "url": "URL#5931584"}]}}}